wsvcs/__init__.py
wsvcs/client/__init__.py
wsvcs/client/manifest.py
wsvcs/client/reverse_dict.py
wsvcs/client/walktree.py
wsvcs/main.py
wsvcs/pyinstaller.py
wsvcs/server/__init__.py
wsvcs/shared/__init__.py
wsvcs/shared/abstract.py
wsvcs/shared/ainput.py
wsvcs/shared/chunk_reader.py
wsvcs/shared/commands.py
wsvcs/shared/hashfile.py
wsvcs/shared/logging.py
wsvcs/shared/modes.py
wsvcs/shared/packages.py
wsvcs/shared/terminal.py
wsvcs-0.1.0.dist-info/entry_points.txt
wsvcs-0.1.0.dist-info/LICENSE
wsvcs-0.1.0.dist-info/METADATA
wsvcs-0.1.0.dist-info/WHEEL
wsvcs-0.1.0.dist-info/RECORD
