Metadata-Version: 2.1
Name: wsvcs
Version: 0.1.0
Summary: 
Author: Encore Ecosystem
Requires-Python: >=3.12,<3.14
Classifier: Programming Language :: Python :: 3
Classifier: Programming Language :: Python :: 3.12
Requires-Dist: pyinstaller (>=6.10.0,<7.0.0)
Requires-Dist: tqdm (>=4.66.5,<5.0.0)
Requires-Dist: websockets (>=13.0.1,<14.0.0)
